Topo_Tracer/Topo_Tracer_1.py
Topo_Tracer/Topo_Tracer_2.py
Topo_Tracer/__init__.py
topo_tracer-0.1.12.dist-info/licenses/LICENSE.txt
topo_tracer-0.1.12.dist-info/METADATA
topo_tracer-0.1.12.dist-info/WHEEL
topo_tracer-0.1.12.dist-info/top_level.txt
topo_tracer-0.1.12.dist-info/RECORD
