Metadata-Version: 2.4
Name: Topo_Tracer
Version: 0.1.12
Summary: Package to extract and trace the topological skeleton of a 2-order stress tensor field
Author-email: Niclas Brandt <niclasbrandt97@gmail.com>
Classifier: Programming Language :: Python :: 3
Classifier: License :: OSI Approved :: MIT License
Classifier: Operating System :: OS Independent
Requires-Python: >=3.7
License-File: LICENSE.txt
Requires-Dist: requests>=2.0
Requires-Dist: numpy>=1.20
Dynamic: license-file
